[
  {
    "model": "folio.Skill",
    "fields": {
      "skill": 1,
      "type": "language",
      "level": 100,
      "experience": 5,
      "logo_skill": "assets/logos/HTML5_Badge.svg"
    }
  },
  {
    "model": "folio.Skill",
    "fields": {
      "skill": 2,
      "type": "language",
      "level": 100,
      "experience": 5,
      "logo_skill": "assets/logos/CSS3_logo.svg"
    }
  },
  {
    "model": "folio.Skill",
    "fields": {
      "skill": 3,
      "type": "language",
      "level": 100,
      "experience": 5,
      "logo_skill": "assets/logos/Sass_Logo_Color.svg"
    }
  },
  {
    "model": "folio.Skill",
    "fields": {
      "skill": 4,
      "type": "language",
      "level": 95,
      "experience": 5,
      "logo_skill": "assets/logos/JavaScript-logo.png"
    }
  },
  {
    "model": "folio.Skill",
    "fields": {
      "skill": 10,
      "type": "language",
      "level": 80,
      "experience": 5,
      "logo_skill": "assets/logos/VueJS-logo.svg"
    }
  },
  {
    "model": "folio.Skill",
    "fields": {
      "skill": 11,
      "type": "language",
      "level": 65,
      "experience": 1.5,
      "logo_skill": "assets/logos/ReactJS-logo.svg"
    }
  },
  {
    "model": "folio.Skill",
    "fields": {
      "skill": 8,
      "type": "language",
      "level": 40,
      "experience": 1,
      "logo_skill": "assets/logos/python-logo.png"
    }
  },
  {
    "model": "folio.Skill",
    "fields": {
      "skill": 9,
      "type": "language",
      "level": 40,
      "experience": 1,
      "logo_skill": "assets/logos/django-logo-negative.svg"
    }
  },
  {
    "model": "folio.Skill",
    "fields": {
      "skill": 5,
      "type": "language",
      "level": 90,
      "experience": 5,
      "logo_skill": "assets/logos/bootstrap-logo.svg"
    }
  },
  {
    "model": "folio.Skill",
    "fields": {
      "skill": 6,
      "type": "language",
      "level": 80,
      "experience": 1.5,
      "logo_skill": "assets/logos/tailwind-logo.svg"
    }
  },
  {
    "model": "folio.Skill",
    "fields": {
      "skill": 12,
      "type": "language",
      "level": 90,
      "experience": 3,
      "logo_skill": "assets/logos/wordpress-logo.svg"
    }
  },
  {
    "model": "folio.Skill",
    "fields": {
      "skill": 13,
      "type": "logiciel",
      "level": 90,
      "experience": 5,
      "logo_skill": "assets/logos/gitlab.svg"
    }
  },
  {
    "model": "folio.Skill",
    "fields": {
      "skill": 14,
      "type": "logiciel",
      "level": 85,
      "experience": 1,
      "logo_skill": "assets/logos/github-mark-white.svg"
    }
  },
  {
    "model": "folio.Skill",
    "fields": {
      "skill": 15,
      "type": "logiciel",
      "level": 90,
      "experience": 2,
      "logo_skill": "assets/logos/photoshop-logo.svg"
    }
  },
  {
    "model": "folio.Skill",
    "fields": {
      "skill": 16,
      "type": "logiciel",
      "level": 90,
      "experience": 1,
      "logo_skill": "assets/logos/affinity-design-logo.svg"
    }
  },
  {
    "model": "folio.Skill",
    "fields": {
      "skill": 17,
      "type": "logiciel",
      "level": 90,
      "experience": 1,
      "logo_skill": "assets/logos/affinity-photo-logo.svg"
    }
  },
  {
    "model": "folio.Skill",
    "fields": {
      "skill": 18,
      "type": "logiciel",
      "level": 95,
      "experience": 8,
      "logo_skill": "assets/logos/gimp-logo.svg"
    }
  },
  {
    "model": "folio.Skill",
    "fields": {
      "skill": 19,
      "type": "logiciel",
      "level": 90,
      "experience": 1,
      "logo_skill": "assets/logos/logo-figma.svg"
    }
  },
  {
    "model": "folio.Skill",
    "fields": {
      "skill": 20,
      "type": "logiciel",
      "level": 90,
      "experience": 1,
      "logo_skill": "assets/logos/Adobe_XD_CC_icon.svg"
    }
  }
]